caoscrawler/__init__.py
caoscrawler/authorize.py
caoscrawler/cfood-schema.yml
caoscrawler/config.py
caoscrawler/crawl.py
caoscrawler/debug_tree.py
caoscrawler/default_converters.yml
caoscrawler/default_transformers.yml
caoscrawler/exceptions.py
caoscrawler/extension-converters-config-schema.yml
caoscrawler/identifiable.py
caoscrawler/identifiable_adapters.py
caoscrawler/logging.py
caoscrawler/scanner.py
caoscrawler/stores.py
caoscrawler/sync_graph.py
caoscrawler/sync_node.py
caoscrawler/transformer_functions.py
caoscrawler/utils.py
caoscrawler/validator.py
caoscrawler/version.py
caoscrawler/converters/__init__.py
caoscrawler/converters/converters.py
caoscrawler/converters/hdf5_converter.py
caoscrawler/converters/rocrate.py
caoscrawler/converters/spss.py
caoscrawler/converters/xml_converter.py
caoscrawler/converters/zipfile_converter.py
caoscrawler/macros/__init__.py
caoscrawler/macros/macro_yaml_object.py
caoscrawler/scripts/__init__.py
caoscrawler/scripts/generators.py
caoscrawler/structure_elements/__init__.py
caoscrawler/structure_elements/rocrate_structure_elements.py
caoscrawler/structure_elements/structure_elements.py
caoscrawler-0.13.0.dist-info/LICENSE
caoscrawler-0.13.0.dist-info/METADATA
caoscrawler-0.13.0.dist-info/WHEEL
caoscrawler-0.13.0.dist-info/entry_points.txt
caoscrawler-0.13.0.dist-info/top_level.txt
caoscrawler-0.13.0.dist-info/RECORD
