Metadata-Version: 2.1
Name: caoscrawler
Version: 0.13.0
Summary: A new crawler for LinkAhead
Author: Alexander Schlemmer
Author-email: alexander.schlemmer@ds.mpg.de
Classifier: Programming Language :: Python :: 3
Classifier: License :: OSI Approved :: GNU Affero General Public License v3 or later (AGPLv3+)
Classifier: Operating System :: OS Independent
Requires-Python: >=3.9
License-File: LICENSE
Requires-Dist: caosadvancedtools >=0.14.0
Requires-Dist: importlib-resources
Requires-Dist: linkahead >=0.16.0
Requires-Dist: odfpy
Requires-Dist: packaging
Requires-Dist: pandas
Requires-Dist: pyarrow
Requires-Dist: pyyaml
Requires-Dist: yaml-header-tools >=0.2.1
Provides-Extra: h5-crawler
Requires-Dist: h5py >=3.8 ; extra == 'h5-crawler'
Requires-Dist: numpy ; extra == 'h5-crawler'
Provides-Extra: rocrate
Requires-Dist: rocrate ; extra == 'rocrate'
Provides-Extra: spss
Requires-Dist: pandas[spss] ; extra == 'spss'
